{
  "global": {
    "see-all": "查看全部",
    "unknown-contributor": "旅行者",
    "copy-url": "URL已複製",
    "all": "全部",
    "no": "否",
    "yes": "是",
    "close": "關閉",
    "go-back": "返回",
    "login": "登入",
    "logout": "登出",
    "ask-logout": "係咪確定要登出？",
    "ask-country": "請選擇護照發行地",

    "require-login": "此功能為會員專屬，請您先登入會員再行瀏覽",
    "update-title": "提醒更新版本",
    "update-msg": "錯誤修正之後,已改善了使用性的最新版本已登錄",
    "update-ok": "更新",
    "type-empty": "請輸入內容"
  },
  "date": {
    "mon": "星期一",
    "tue": "星期二",
    "wed": "星期三",
    "thu": "星期四",
    "fri": "星期五",
    "sat": "星期六",
    "sun": "星期天"
  },
  "month": {
    "january": "一月",
    "february": "二月",
    "march": "三月",
    "april": "四月",
    "may": "五月",
    "june": "六月",
    "july": "七月",
    "august": "八月",
    "september": "九月",
    "october": "十月",
    "november": "十一月",
    "december": "十二月"
  },
  "login": {
    "login-email": "以電子郵件登入 ",
    "login-google": "以Google登入",
    "login-facebook": "以Facebook登入",
    "login": "登入",
    "login-fail": "登入失敗。請再次確認電子郵件及密碼是否正確",
    "email": "電子信箱",
    "password": "密碼",
    "sign-up": "註冊",
    "error-empty-name": "請輸入您的名字",
    "error-empty-nickname": "請輸入一個暱稱",
    "error-empty-email": "請輸入您的電子郵件",
    "error-incorect-email": "您的信箱格式錯誤。",
    "error-empty-password": "請輸入密碼",
    "error-password-more-six": "Your Password must be more than 6 character.",
    "error-empty-country": "請輸入您的國家",
    "register-fail": "'Register fail'",
    "guest": "訪客",
    "forgot-password": "忘記密碼？",
    "cancel": "取消",
    "agree": "同意",
    "username-taken": "用戶名已被使用",
    "ok": "確認",
    "name": "名字",
    "alias": "暱稱",
    "nationality": "護照發行地",
    "already-have-an-account": "已有帳號？登入"
  },
  "link-account": {
    "cannot-connected": "此帳戶無法連接 (有疑問請聯絡 support@creatrip.com)",

    "header": "帳戶連結",
    "not-connected": "尚未連結",
    "no-account-connected": "冇可以連結嘅帳戶",
    "connect": "連結",
    "alert-merge-account": "此電郵地址已被使用，如繼續，新帳戶資料將會同社交媒體自動連結",
    "success-linking": "帳戶連結成功。",
    "fail-linking": "信箱重複。",
    "connected": "已連結",
    "request-cancel-linking": "請問係咪拒絕連結帳號？",
    "yes": "係",
    "no": "唔係"
  },
  "travel": {
    "tips": "小貼士",
    "category": "類別"
  },
  "home": {
    "travel": "旅行資訊 ",
    "suggest-keyword": "Creatrip會員專屬優惠",
    "title-suggest-one": "行程優惠",
    "content-suggest-one": "韓國熱門行程高達50%優惠",
    "title-suggest-two": "Cafe優惠券",
    "content-suggest-two": "精選全國100間Cafe獨家優惠",
    "title-suggest-three": "餐廳優惠券",
    "content-suggest-three": "韓國人私心推薦餐廳",
    "title-suggest-four": "外賣服務",
    "content-suggest-four": "體驗韓國人外賣文化",
    "title-suggest-five": "韓國代購",
    "content-suggest-five": "當地流行商品直送屋企",
    "title-suggest-six": "旅行小貼士",
    "content-suggest-six": "出發前須知＆即時旅行情報",
    "search-placeholder": "搜尋\"弘大或景福宮韓服\"",
    "search-city": "城市",
    "spot": "{{city}}的人氣景點",
    "blog": "{{city}}的旅遊攻略",
    "all": "See all +{{number}}",
    "city": "城市",
    "travel-info": "旅遊資訊",
    "reservation-discounts": "預約行程",
    "main-coupon": "優惠券",
    "korean-culture": "韓國文化",
    "accomodation": "住宿預訂",
    "flight-info": "航班指南",
    "key-guide": "來韓須知",
    "entracnce-info": "入境須知",
    "exchange-info": "換錢資訊",
    "tex-refund-info": "退稅攻略",
    "accommodation-info": "住宿指南",
    "duty-free-info": "免稅店折扣優惠",
    "hanbok-info": "韓服體驗",
    "delivery-guide": "美食外送",
    "visa-info": "所需簽證",
    "transportation": "交通資訊",
    "weather-today": "現時天氣",
    "currency-rate": "今日匯率",
    "korea-news": "韓國新知"
  },
  "weather": {
    "weather": "今日天气"
  },
  "flightTime": {
    "Taiwan": "臺灣",
    "Hong-Kong": "香港",
    "Thailand": "泰國",
    "Indonesia": "印尼",
    "Malaysia": "馬來西亞",
    "Macau": "澳門",
    "Philippines": "菲律賓",
    "China": "中國",
    "UnitedState": "美國",
    "Singapore": "新加坡",
    "Japan": "日本",
    "India": "印度"
  },
  "search": {
    "search": "搜尋",
    "blog": "旅遊攻略",
    "spot": "旅遊景點",
    "sort-date": "最新發表",
    "sort-like": "人氣排序",
    "search-blog": "{{city}}的{{word}} 旅遊攻略搜尋結果",
    "search-blog-empty-city": "{{word}} 旅遊攻略搜尋結果 ",
    "search-spot": "{{city}}的{{word}} 旅遊攻略搜尋結果",
    "search-spot-empty-city": "{{word}} 旅行景點搜尋結果"
  },
  "category": {
    "recent": "最新資料",
    "exchange": "今日匯率",
    "notice": "網站公告",
    "notice-tag-name": "公告",
    "meet-friend": "相見歡吧",
    "meet-friend-tag-name": "相見歡吧",
    "korean-learn": "韓語小教室",
    "korean-learn-tag-name": "韓語小教室",
    "korean-culture": "韓國文化",
    "korean-culture-tag-name": "韓國文化",
    "korean-news": "韓國新聞",
    "korean-news-tag-name": "韓國新聞"
  },
  "meet-friend": {
    "all": "全部",
    "my-post": "我的文章 ",
    "my-reply": "我的留言",
    "see-more": "看更多",
    "please-enter-title": "請輸入標題",
    "please-write-contents": "請輸入内容",
    "go-back": "取消",
    "confirm": "送出",
    "reply": "回覆"
  },
  "exchange": {
    "title": "今日匯率",
    "name": "換錢所名稱",
    "updated": "最近更新時間",
    "bank-currency-rate": "匯率換算",
    "exchange-shop-rate": "找換店匯率"
  },
  "reserve": {
    "select-an-option": "請選擇",

    "need-more-amount": " 訂單未滿₩{{totalPrice}}，請繼續落單，多謝。",

    "delivery-fee": "外賣費",

    "benefit": "預約及會員優惠",
    "my-reserve": "我的預約",
    "reserve": "免費預約",
    "discount": "會員優惠",
    "reserve-date": "預約日期",
    "reserve-date-select": "選擇預約日期",
    "need-date": "請選擇日期",
    "check-date": "該日期無法預約，請選擇其他日期",
    "need-product": "尚未選擇預約服務",
    "need-more-product": "預約人數未達最低標準，請重新修改人數",
    "so-much-product": "已超過最多可預約的數量",
    "reserve-service": "預約方案",
    "reserve-time": "預約時間",
    "time-rank-first": "第一優先",
    "time-rank-second": "第二次序",
    "time-rank-third": "第三次序",
    "final-price": "最終價格",
    "unnecessary-payment": " 預約完成後，至現場付款即可 ",
    "please-input-name": "請輸入姓名",
    "please-select-country": "請選擇護照發行地",
    "please-input-email": "請輸入電子郵件地址",
    "invalid-email": "Email輸入不正確",
    "empty-error": "請輸入內容",
    "please-input-social": "請輸入通訊軟體帳號",
    "name": "預約代表人姓名",
    "name-placeholder": "護照上的英文名字",
    "country": "護照發行地",
    "country-select": "請選擇護照發行地",
    "email": "電子郵件地址",
    "email-placeholder": "正確的電子郵件地址",
    "social-id": "Line/Whatsapp ID（請註明）",
    "social-placeholder": "請輸入LINE或Whatsapp ID",
    "user-request": "地址（預訂外送者填寫）",
    "request-placeholder": "請輸入正確英/韓地址",
    "reserve-birthday": "出生年月日",
    "reserve-birthday-place-holder": "出生年月日 Ex) 1999.01.01",
    "reserve-delivery-address": "外送地址",
    "reserve-delivery-address-place-holder": "正確的外送地址（包括房號）",
    "nationality_name": "中文姓名",
    "reserve-telephone": "聯絡電話",
    "reserve-telephone-place-holder": "可進行聯絡的電話號碼 Ex) +821012341234",
    "reserve-nationality-name": "中文姓名",
    "reserve-nationality-name-place-holder": "Ex) 王惠敏",
    "reserve-hotel-name": "飯店名稱",
    "reserve-hotel-name-place-holder": "飯店名稱",
    "reserve-flight-number": "航班號",
    "reserve-flight-number-place-holder": "Ex) OZ108",
    "reserve-gender": "性別",
    "reserve-gender-place-holder": "請選擇性別",
    "need-payment": "本預約需要先付款\n即將跳至結帳頁面",
    "need-confirm": "本預約需經管理者確認\n 結果可於營業日1日內在’我的預約’中確認",
    "complete-reserve": "已完成預約",
    "check-reserve": "預約過程發生問題。\n 請重新確認已輸入的資訊",
    "service-complete": "選擇完畢",
    "next": "下一步",
    "reset": "修改",
    "confirm": "完成",
    "reserve-complete": "完成預約"
  },
  "reserve-detail": {
    "title": "{{name}}",
    "code": "預約號碼",
    "status": {
      "ready": "等待中",
      "payment": "等待付款",
      "confirm": "等待確認",
      "refund": "退款",

      "complete": "預約完成",
      "cancel": "預約取消",
      "used": "使用完成"
    },
    "detail-page-status": {
      "payment-waiting": "等待付款中",
      "payment-complete": "付款完成",
      "locale-payment": "免費預約，現場付款"
    },
    "select-product-placeholder": "請選擇方案",
    "input-info-title": "請輸入正確預約資訊",
    "final-check-title": "請再次確認您填寫的預約資訊",
    "reserve-title": "預約方案",
    "reserve-name": "預約者姓名",
    "reserve-email": "預約者電子信箱",
    "reserve-date": "預約日期",
    "reserve-time": "預約時間",
    "reserve-service": "預約服務",
    "reserve-voucher": "優惠代碼",
    "reserve-request": "請輸入外送的配送地址",
    "reserve-price": "總金額（實際結帳金額以現場為主）",
    "reserve-count": "{{count}}組",
    "reserve-cancel": "取消預約",
    "go-spot": "查看店家資訊",
    "product": "服務",
    "date": "日期",
    "count": "人數",
    "paid-reserve": " 退款處理時間最多為7個工作天 ，有任何問題請來信至 support@creatrip.com 詢問",
    "cancel-message": "*欲修改預約資訊時，請取消後再重新預約。已完成付款的預約於取消後即會進行退款，重新預約時仍需進行結帳。 ",
    "already-cancel": "預約已取消",
    "alert-cancel": "確定要刪除此選項嗎？",
    "cancel-complete": "預約已取消",
    "cancel-fail": {
      "voucher": "您的預約無法取消，請來信 support@creatrip.com告知，專員將儘快為您處理。",
      "today": "很抱歉，相關預約規範中皆有說明，此預約無法於體驗前1日進行取消，請來信 support@creatrip.com告知，專員將儘快為您處理。",
      "late": "很抱歉，您的預約逾期，無法進行取消 。",
      "already": "您的預約已取消。",
      "fail": "很抱歉，您的預約要求目前無法受理，請稍後重新再試一次。",
      "refund": "本行程取消後無法獲得任何退款，請問您是否要繼續？"
    },
    "gender": {
      "male": "남성",
      "female": "여성"
    },
    "spot-remarks": {
      "free-reserve": "免費預約，現場付款",
      "deposit-reserve": "需預付訂金，現場補足消費差額",
      "refund-3-day": "體驗日前3天內，無法進行退改",
      "refund-5-day": "體驗日前5天內，無法進行退改",
      "refund-7-day": "體驗日前7天內，無法進行退改",
      "unable-refund": "售出後不接受退改",
      "mobile-voucher": "只需出示手機預約憑證",
      "print-voucher": "需出示列印紙本憑證",
      "change-ticket": "需兌換成實體票券",
      "no-ticket": "無需兌換成實體票券",
      "require-4-hour": "體驗時間約4小時",
      "require-6-hour": "體驗時間約6小時",
      "require-8-hour": "體驗時間約8小時",
      "require-date": "需於指定日期進場",
      "member-auth": "現場出示Creatrip會員證明享優惠",
      "guarantee": "特約商家保障",
      "group-join": "隨機湊團行程",
      "language-korean": "韓文可能",
      "language-mandarin": "中文可能",
      "language-english": "英文可能",
      "show-coupon": "現場出示Creatrip專屬優惠券以享有折價。"
    }
  },
  "payment": {
    "success": "{{name}} 已完成預約",
    "fail": "{{name}} 預約失敗",
    "payment-complete": "查看我的預約內容",
    "payment-fail-retry": "重新結帳"
  },
  "map": {
    "search-placeholder": "搜尋",
    "search": "以現在的所在地進行搜尋",
    "dining": "餐廳",
    "cafe": "咖啡",
    "attraction": "景點",
    "accommodation": "住宿",
    "shopping": "購物",
    "activity": "體驗",
    "transportation": "交通",
    "all": "全部",
    "request_turn_on_location_permission": "您必须打开位置权限才能继续.",
    "request_turn_on_location_permission_failed": "您的位置现在无法使用."
  },
  "about": {
    "my-page": "我的頁面（會員證明）",
    "my-reserve": "預約",
    "my-coupon": "優惠券",
    "my-like": "收藏"
  },
  "my-page": {
    "title": "我的頁面（會員證明）",
    "member": "Creatrip 인증회원에게 제휴혜택을 제공해 주세요",
    "benefit": "此畫面為Creatrip會員憑證。",
    "social-user": "僅有透過電子信箱註冊的會員，可以在Creatrip網站變更密碼。若您是使用Facebook或Google快速登入，則必須在您原有的Facebook、Google平台變更密碼。",
    "show-benefit": "會員優惠",
    "nickname": "暱稱",
    "home": "居住城市",
    "introduce": "自我介紹",
    "id": "帳號",
    "change-password": "修改密碼",
    "language": "語言",
    "english": "中文繁體（台灣）",
    "personal-settings": "變更個人資訊",
    "duplicate-nickname": "重複的暱稱。",

    "image-fail": "個人主頁照片變更失敗",
    "travel-info": "旅遊資訊",
    "reservation-benefits": "行程優惠",
    "reservation": "我的預約",
    "delete": "刪除",
    "book-again": "再次預約",
    "cancel": "取消",
    "canceled": "已取消",
    "expired": "已使用ุ",
    "verify-creatrip-membership": "會員証明頁面",
    "step": "第{{step}}步",
    "how-to-verify-creatrip-membership": "如何驗證Creatrip成員資格",
    "free-online-reservation": "免費預約",
    "onsite-payment": "現場付款",
    "info": "查看詳情",
    "please-enter-booking-password": "請輸入預約密碼",
    "voucher-regraded": "輸入密碼後，憑證將被視為已過期且無效。",
    "password": "密碼",
    "cancel-popup": "取消",
    "confirm": "確認",
    "cancel-reversation": "取消",
    "current-password": "舊密碼",
    "new-password": "新密碼",
    "retype-new-password": "再確認一次新密碼",
    "change": "變更密碼"
  },
  "alert": {
    "notifications": "通知",
    "all": "所有",
    "reservation": "預約",
    "event": "活動",
    "announcement": "公告"
  },
  "change-password": {
    "title": "修改密碼",
    "current": "當前密碼",
    "notice": "請輸入5位以上的密碼",
    "new": "新密碼",
    "check": "再次輸入新密碼",
    "change": "修改",
    "new-error": "請輸入5位以上的密碼",
    "check-error": "密碼不一致",
    "social-user": "以Google或Facebook加入者欲修改密碼時，須於該網站中進行修改",
    "confirm": "確認",
    "check-password": "輸入密碼",
    "success": "密碼修改完成 "
  },
  "member-benefit": {
    "title": "會員優惠",
    "reserve-title": "{{spotName}} 會員優惠",
    "show-list": "查看清單",
    "first-title": "1. 特約商店優惠",
    "first-explain": "不必事前預約，直接抵達現場消費時，出示Creatrip會員證明，以享有獨家優惠",
    "second-title": "2. 行程預約服務",
    "second-explain": "在Creatrip事前預約，現場出示會員憑證，享熱門韓國行程、韓服體驗超值折扣"
  },
  "membership-method": {
    "visit-creatrip-partner-store": "訪問Creatrip合作商店",
    "verify-creatrip-membership-onsite": "現場出示Creatrip會員證明享優惠",
    "if-booked-in-advance": "如果您提前預訂，請在我的預約頁面上出示預約確認信",
    "enjoy-benefits": "享受Creatrip會員優惠"
  },
  "my-reserve": {
    "title": "我的預約",
    "product": "{{item}} 外 {{count}} 個",
    "people-count": "共 {{count}}組",
    "empty-reserve": "沒有任何預約內容\n 跳至預約服務清單",
    "yes": "是",
    "no": "否"
  },
  "reservation": {
    "my-reservation": "我的预约"
  },
  "my-like": {
    "title": "我的收藏",
    "blog": "旅遊攻略",
    "spot": "旅遊景點",
    "product": "{{item}} 外 {{count}} 個",
    "people-count": "共 {{count}}組",
    "empty-reserve": "沒有任何預約內容\n 跳至預約服務清單",
    "yes": "是",
    "no": "否"
  },
  "spot": {
    "select-blog": "請選擇要查看的後記",
    "review": "回覆",
    "question": "提問",
    "reply": "回覆",
    "empty-info": "尚無相關資訊",
    "detail": "詳細資訊",
    "more-info": "注意事項",
    "precaution": "注意事項",
    "open-time": "營業時間",
    "opening-hours": "營業時間",
    "product": "價位表",
    "price-info": "價格",
    "confirm": "確認",
    "show-more": "點我查看",
    "address": "地址",
    "show-all-review": "查看所有回覆",
    "show-link": "後記",
    "go-reserve": "點我預約",
    "go-benefit": "領取優惠",
    "go-url": "點我預約",
    "see-more": "看更多",
    "402-reviews": "共有402則回覆",
    "20-hours-ago": "20小時前",
    "further-readings": "其他推薦",
    "related-blogs": "Related Blog",
    "all": "所有",
    "latest": "最新發表",
    "popular": "人氣排序",
    "blog": "旅遊攻略",
    "ticket-options": "選擇方案"
  },
  "blog": {
    "select-spot": "請選擇要查看的資訊",
    "reply": "撰寫回文",
    "show-link": "有關經點",
    "go-reserve": "點我預約",
    "go-benefit": "領取優惠",
    "go-url": "點我預約",
    "all": "所有",
    "city": "城市",
    "latest": "最新發表",
    "best": "人氣排序",
    "blog": "旅遊攻略",
    "19-hours-ago": "“19小時”前",
    "a-day-ago": "一天前",
    "detail": {
      "reviews": "評價",
      "402-reviews": "共有402則回覆",
      "write-a-review": "寫回覆",
      "reply": "回覆",
      "edit": "編輯",
      "delete": "刪除",
      "see-more": "看更多",
      "related-travel-blogs": "推薦的旅遊攻略",
      "related-places": "查看簡介",
      "reserve": "快速預定"
    }
  },
  "review": {
    "review": "回覆",
    "reply": "回覆",
    "delete": "刪除",
    "review-count": "共 {{count}}個後記",
    "review-length": "請留下10字以上的後記",
    "placeholder": "請留下 10字以上的後記",
    "is-question": "提問",
    "write": "發表",
    "setting-blog": "旅遊攻略",
    "setting-spot": "旅遊景點",
    "setting-best": "人氣排序",
    "setting-latest": "最新發表",
    "button-pay": "結帳"
  },

  "need-update": "請將app更新至最新版本",
  "proxy-shopping": "韓國代購",
  "new-product": "新品上架",

  "ask-for-product": "商品問價",
  "sub-ask-for-product": "想買嘅商品都可以問價",

  "ask-question": "聯絡我哋",
  "ask-question-send-email": "發送郵件",
  "currency-update-time": "更新時間",
  "ask-youremail": "E-MAIL",
  "ask-yourname": "姓名",
  "ask-description": "如果有任何疑問，可以喺度留言，我哋會喺24小時內回覆您。",
  "buy-now": "點我下單",
  "warning-fill-full": "請填寫全部內容",
  "tip-forgot-password": "電郵寄送失敗，請試用Google或Facebook登入",
  "success-send-mail-forgot-password": "已收到密碼變更要求，請檢查信箱。",
  "fail-send-mail-forgot-password": "信件發送失敗。",
  "contact-us": "CONTACT US"
}
